hbdk/.gitignore
hbdk/LICENSE.txt
hbdk/README.md
hbdk/__init__.py
hbdk/_hbir_base.so
hbdk/checker.py
hbdk/compiler.py
hbdk/config.py
hbdk/hbir_base.py
hbdk/hbir_helper.py
hbdk/bin/hbdk-cc
hbdk/bin/hbdk-disas
hbdk/bin/hbdk-gen-license
hbdk/bin/hbdk-hbm-attach
hbdk/bin/hbdk-layout-convert
hbdk/bin/hbdk-model-check
hbdk/bin/hbdk-pack
hbdk/bin/hbdk-perf
hbdk/bin/hbdk-resize
hbdk/bin/hbdk-sim
hbdk/entrypoint/__init__.py
hbdk/entrypoint/entrypoint_hbdk_cc.py
hbdk/entrypoint/entrypoint_hbdk_disas.py
hbdk/entrypoint/entrypoint_hbdk_gen_license.py
hbdk/entrypoint/entrypoint_hbdk_hbm_attach.py
hbdk/entrypoint/entrypoint_hbdk_layout_convert.py
hbdk/entrypoint/entrypoint_hbdk_model_check.py
hbdk/entrypoint/entrypoint_hbdk_pack.py
hbdk/entrypoint/entrypoint_hbdk_perf.py
hbdk/entrypoint/entrypoint_hbdk_resize.py
hbdk/entrypoint/entrypoint_hbdk_sim.py
hbdk/lib64/libc10.so
hbdk/lib64/libgomp-a34b3233.so.1
hbdk/lib64/libhbdk-frontend-shared.so
hbdk/lib64/libhbdk_sim_x86.so
hbdk/lib64/libhbrt_x86_hook.so
hbdk/lib64/libtorch.so
hbdk/lib64/aarch64/libhbrt_bayes_aarch64.so
hbdk/lib64/aarch64/libhbrt_bayes_aarch64_hook.so
hbdk/lib64/aarch64/libhbrt_bernoulli_aarch64.so
hbdk/lib64/aarch64/libhbrt_bernoulli_aarch64_hook.so
hbdk/lib64/aarch64_gcc_11_2/libhbrt_bayes_aarch64.so
hbdk/lib64/aarch64_gcc_11_2/libhbrt_bayes_aarch64_hook.so
hbdk/lib64/aarch64_gcc_9_3/libhbrt_bayes_aarch64.so
hbdk/lib64/aarch64_gcc_9_3/libhbrt_bayes_aarch64_hook.so
hbdk/lib64/aarch64_gcc_9_3/libhbrt_bernoulli_aarch64.so
hbdk/lib64/aarch64_gcc_9_3/libhbrt_bernoulli_aarch64_hook.so
hbdk/lib64/x86/DEPRECATION_WARNING
hbdk/lib64/x86/libhbdk_sim_x86.so
hbdk/lib64/x86/libhbrt_bayes_x86.so
hbdk/operator/__init__.py
hbdk/operator/channel_argmax.py
hbdk/operator/conversion.py
hbdk/operator/dpp.py
hbdk/operator/lut.py
hbdk/proto/onnx_pb2.py
hbdk/sbin/hbdk-run-model-bayes-aarch64
hbdk/sbin/hbdk-run-model-bernoulli-aarch64
hbdk/sbin/hbdk-run-model-x86
hbdk/sbin/ml-adviser
hbdk/sbin/tiling_model_de10f31f71.pt
dgdk-1.0.0.dist-info/DESCRIPTION.rst
dgdk-1.0.0.dist-info/METADATA
dgdk-1.0.0.dist-info/WHEEL
dgdk-1.0.0.dist-info/entry_points.txt
dgdk-1.0.0.dist-info/top_level.txt
dgdk-1.0.0.dist-info/RECORD
