Metadata-Version: 2.1
Name: dgdk
Version: 1.0.0
Summary: D-Robotics Compiler Toolkit
Home-page: https://developer.d-robotics.cc/
Author: D-Robotics, Inc
Author-email: developer@d-robotics.cc
License: Copyright (C) D Robotics Inc. - All Rights Reserved
